daqm/__init__.py
daqm/data/__init__.py
daqm/data/columns.py
daqm/data/data.py
daqm/data/data_frame.py
daqm/data/db_table.py
daqm/data/query.py
daqm/utils/constant.py
daqm/utils/type_convert.py
daqm-0.1.7.dist-info/LICENSE
daqm-0.1.7.dist-info/METADATA
daqm-0.1.7.dist-info/WHEEL
daqm-0.1.7.dist-info/top_level.txt
daqm-0.1.7.dist-info/RECORD
