Metadata-Version: 2.1
Name: daqm
Version: 0.1.7
Summary: Data Analysis Query Machine
Home-page: https://github.com/linewalks/daqm
Author: Linewalks
Author-email: web@linewalks.com
License: UNKNOWN
Platform: UNKNOWN
Classifier: Programming Language :: Python :: 3
Classifier: License :: OSI Approved :: MIT License
Classifier: Operating System :: OS Independent
Requires-Python: >=3.6
Requires-Dist: numpy
Requires-Dist: pandas
Requires-Dist: sqlalchemy
